helsinki_gdpr/__init__.py
helsinki_gdpr/models.py
helsinki_gdpr/types.py
helsinki_gdpr/urls.py
helsinki_gdpr/views.py
helsinki_profile_gdpr_api-0.2.0.dist-info/LICENSE
helsinki_profile_gdpr_api-0.2.0.dist-info/METADATA
helsinki_profile_gdpr_api-0.2.0.dist-info/WHEEL
helsinki_profile_gdpr_api-0.2.0.dist-info/top_level.txt
helsinki_profile_gdpr_api-0.2.0.dist-info/RECORD
