Metadata-Version: 2.1
Name: helsinki-profile-gdpr-api
Version: 0.2.0
Summary: Django app for implementing Helsinki profile GDPR API
Home-page: https://github.com/City-of-Helsinki/helsinki-profile-gdpr-api
Author: City of Helsinki
Author-email: dev@hel.fi
License: MIT License
Project-URL: Bug Tracker, https://github.com/City-of-Helsinki/helsinki-profile-gdpr-api/issues
Classifier: Environment :: Web Environment
Classifier: Framework :: Django
Classifier: Intended Audience :: Developers
Classifier: License :: OSI Approved :: MIT License
Classifier: Operating System :: OS Independent
Classifier: Programming Language :: Python
Classifier: Programming Language :: Python :: 3
Classifier: Programming Language :: Python :: 3 :: Only
Classifier: Programming Language :: Python :: 3.7
Classifier: Programming Language :: Python :: 3.8
Classifier: Programming Language :: Python :: 3.9
Classifier: Topic :: Internet :: WWW/HTTP
Classifier: Topic :: Internet :: WWW/HTTP :: Dynamic Content
Classifier: Topic :: Software Development :: Libraries :: Python Modules
Requires-Python: >=3.7
License-File: LICENSE
Requires-Dist: Django
Requires-Dist: djangorestframework
Requires-Dist: django-helusers
Requires-Dist: drf-oidc-auth
